peregrinus/__init__.py
peregrinus/world/__init__.py
peregrinus/world/celestial/__init__.py
peregrinus/world/celestial/planet.py
peregrinus/genesis/__init__.py
peregrinus/genesis/celestial/__init__.py
peregrinus-0.1.0.dist-info/entry_points.txt
peregrinus-0.1.0.dist-info/WHEEL
peregrinus-0.1.0.dist-info/METADATA
peregrinus-0.1.0.dist-info/top_level.txt
peregrinus-0.1.0.dist-info/LICENSE
peregrinus-0.1.0.dist-info/RECORD
