Metadata-Version: 2.1
Name: peregrinus
Version: 0.1.0
Summary: adventures in python
Author: Thomas Reiter
License: Apache-2.0
Keywords: adventure,alter ego
Home-page: https://pypi.org/project/peregrinus
Project-URL: Repository, https://github.com/tom65536/peregrinus
Project-URL: Bug Tracker, https://github.com/tom65536/peregrinus/issues
Project-URL: Documentation, https://peregrinus.readthedocs.io
Project-URL: ChangeLog, https://github.com/tom65536/peregrinus/blob/master/ChangeLog.rst
Classifier: Development Status :: 1 - Planning
Classifier: Environment :: Console
Classifier: Intended Audience :: End Users/Desktop
Classifier: License :: OSI Approved :: Apache Software License
Classifier: Operating System :: OS Independent
Classifier: Programming Language :: Python
Classifier: Programming Language :: Python :: 3 :: Only
Classifier: Topic :: Games/Entertainment :: Role-Playing
Classifier: Typing :: Typed
Requires-Python: >=3.6
